{
  "font": {
    "family": {
      "name": {
        "value": "'Mulish'"
      },
      "light": {
        "ttf": { "value": "'assets/fonts/Mulish-Light.ttf'" },
        "woff": { "value": "'assets/fonts/Mulish-Light.woff'" },
        "woff2": { "value": "'assets/fonts/Mulish-Light.woff2'" }
      },
      "regular": {
        "ttf": { "value": "'assets/fonts/Mulish-Regular.ttf'" },
        "woff": { "value": "'assets/fonts/Mulish-Regular.woff'" },
        "woff2": { "value": "'assets/fonts/Mulish-Regular.woff2'" }
      },
      "bold": {
        "ttf": { "value": "'assets/fonts/Mulish-Bold.ttf'" },
        "woff": { "value": "'assets/fonts/Mulish-Bold.woff'" },
        "woff2": { "value": "'assets/fonts/Mulish-Bold.woff2'" }
      }
    },
    "weight": {
      "light": { "value": "300" },
      "regular": { "value": "400" },
      "bold": { "value": "700" }
    }
  }
}
